myrrh/core/delegation/__init__.py
myrrh/core/delegation/_delegation.py
myrrh/core/utils/__init__.py
myrrh/core/utils/_passwd.py
myrrh/core/utils/filemode.py
myrrh/core/utils/merrno.py
myrrh/core/utils/mhandle.py
myrrh/core/utils/misc.py
myrrh/core/utils/mshlex.py
myrrh/core/utils/mstring.py
myrrh/core/utils/mtimer.py
myrrh_core_base-0.1.0.dist-info/AUTHORS.md
myrrh_core_base-0.1.0.dist-info/LICENSE
myrrh_core_base-0.1.0.dist-info/METADATA
myrrh_core_base-0.1.0.dist-info/WHEEL
myrrh_core_base-0.1.0.dist-info/top_level.txt
myrrh_core_base-0.1.0.dist-info/RECORD
