Metadata-Version: 2.1
Name: myrrh_core_base
Version: 0.1.0
Summary: Helpers and global objects for the myrrh project.
Author-email: PyAnjel7 <PyAnjel7@gmail.com>
License: GNU General Public License v3.0 or later
Keywords: baseline:Earendel.
Classifier: License :: OSI Approved :: GNU General Public License v3 or later (GPLv3+)
Classifier: Programming Language :: Python :: 3.12
Requires-Python: >=3.12
License-File: LICENSE
License-File: AUTHORS.md
